uv_version/__init__.py
uv_version/__main__.py
uv_version/cli.py
uv_version/manager.py
uv_version/settings.py
uv_version/collectors/__init__.py
uv_version/collectors/base.py
uv_version/collectors/env_collector.py
uv_version/collectors/git_collector.py
uv_version/collectors/pyproject_collector.py
uv_version/collectors/stdin_collector.py
uv_version/setters/__init__.py
uv_version/setters/base.py
uv_version/setters/print_setter.py
uv_version/setters/pyproject_setter.py
uv_version-0.1.9.post1.dist-info/METADATA
uv_version-0.1.9.post1.dist-info/WHEEL
uv_version-0.1.9.post1.dist-info/entry_points.txt
uv_version-0.1.9.post1.dist-info/top_level.txt
uv_version-0.1.9.post1.dist-info/RECORD
