Metadata-Version: 2.1
Name: uv-version
Version: 0.1.9.post1
Summary: CLI tool for managing package version
Author-email: Alekse Marusich <alekse.marusich@rocshers.com>
License: MIT
Keywords: rocshers,uvxt
Classifier: License :: OSI Approved :: MIT License
Classifier: Intended Audience :: Developers
Classifier: Intended Audience :: Information Technology
Classifier: Intended Audience :: System Administrators
Classifier: Operating System :: OS Independent
Classifier: Topic :: Software Development :: Build Tools
Classifier: Topic :: Software Development :: Libraries :: Python Modules
Classifier: Topic :: Software Development :: Libraries
Classifier: Topic :: Software Development
Classifier: Topic :: System :: Archiving :: Packaging
Classifier: Topic :: System :: Installation/Setup
Classifier: Topic :: System :: Software Distribution
Classifier: Programming Language :: Python :: 3 :: Only
Classifier: Programming Language :: Python :: 3.12
Classifier: Programming Language :: Python :: 3.11
Classifier: Programming Language :: Python :: 3.10
Classifier: Programming Language :: Python :: 3.9
Classifier: Programming Language :: Python :: 3
Classifier: Programming Language :: Python
Requires-Python: >=3.9
Requires-Dist: packaging >=24.2
Requires-Dist: packaging-version-git >=0.1.1
Requires-Dist: packaging-version-increment >=0.1.3
Requires-Dist: tomlkit >=0.13.2
Requires-Dist: typer >=0.13.0
